indepth/__init__.py
indepth/functions.py
indepth/lookup.py
indepth/data/mrc_psycholing.pkl
indepth-1.1.5.dist-info/LICENSE
indepth-1.1.5.dist-info/METADATA
indepth-1.1.5.dist-info/WHEEL
indepth-1.1.5.dist-info/top_level.txt
indepth-1.1.5.dist-info/RECORD
